ethomap/__init__.py
ethomap/cluster.py
ethomap/distance.py
ethomap/dtw.py
ethomap/embed.py
ethomap/sequence.py
ethomap-0.1.1.dist-info/LICENSE.txt
ethomap-0.1.1.dist-info/WHEEL
ethomap-0.1.1.dist-info/METADATA
ethomap-0.1.1.dist-info/RECORD
