Metadata-Version: 2.1
Name: ethomap
Version: 0.1.1
Summary: Generate behavioral embeddings of postural time series.
License: AGPL-3.0
Author: Duncan Mearns
Requires-Python: >=3.9,<4.0
Classifier: License :: OSI Approved :: GNU Affero General Public License v3
Classifier: Programming Language :: Python :: 3
Classifier: Programming Language :: Python :: 3.9
Classifier: Programming Language :: Python :: 3.10
Classifier: Programming Language :: Python :: 3.11
Requires-Dist: joblib (>=1.0.0,<2.0.0)
Requires-Dist: numba (>=0.56.0,<0.57.0)
Requires-Dist: numpy (>=1.23,<2.0)
Requires-Dist: scikit-learn (>=1.1.0,<2.0.0)
Requires-Dist: scipy (>=1.9.0,<2.0.0)
